<?xml version="1.0" encoding="UTF-8"?>
<!DOCTYPE mapper PUBLIC "-//mybatis.org//DTD Mapper 3.0//EN" "http://mybatis.org/dtd/mybatis-3-mapper.dtd">
<mapper namespace="kim.nzxy.auth.models.system.relation.mapper.RouterPermissionMapper">
    <sql id="Base_Column_List">
        router,
      permission
    </sql>
    <resultMap id="BaseResultMap" type="kim.nzxy.auth.models.system.relation.entity.RouterPermission">
        <!--@mbg.generated-->
        <!--@Table router_permission-->
        <id column="router" jdbcType="INTEGER" property="router"/>
        <id column="permission" jdbcType="INTEGER" property="permission"/>
    </resultMap>
    <insert id="insert" parameterType="kim.nzxy.auth.models.system.relation.entity.RouterPermission">
        <!--@mbg.generated-->
        insert into router_permission (router, permission)
        values (#{router,jdbcType=INTEGER}, #{permission,jdbcType=INTEGER})
    </insert>

    <!--auto generated by MybatisCodeHelper on 2019-12-27-->
    <select id="findPermissionByRouter" resultType="java.lang.Integer">
        select permission
        from router_permission
        where router = #{router,jdbcType=INTEGER}
    </select>

    <!--auto generated by MybatisCodeHelper on 2019-12-27-->
    <delete id="deleteByRouter">
        delete
        from router_permission
        where router = #{router,jdbcType=INTEGER}
    </delete>

    <!--auto generated by MybatisCodeHelper on 2019-12-27-->
    <insert id="insertList">
        INSERT INTO router_permission(
        router,
        permission
        )VALUES
        <foreach collection="list" item="element" index="index" separator=",">
            (
            #{element.router,jdbcType=INTEGER},
            #{element.permission,jdbcType=INTEGER}
            )
        </foreach>
    </insert>
</mapper>
